{
  "id": "archelon-skull",
  "name": {
    "de": "Archelon-Schädel",
    "en-GB": "Archelon Skull",
    "en-US": "Archelon Skull",
    "es": "Cráneo archelon",
    "fr": "Crâne d'archelon",
    "it": "Teschio archelone",
    "ja": "アーケロンのあたま"
  },
  "category": "Fossils",
  "games": {
    "nl": {
      "orderable": false,
      "interiorThemes": [
        "Quirky"
      ],
      "sellPrice": {
        "currency": "bells",
        "value": 4000
      },
      "sources": [
        "Underground (dig spot)"
      ]
    },
    "nh": {
      "orderable": false,
      "sources": [
        "Underground (dig spot)"
      ],
      "sellPrice": {
        "currency": "bells",
        "value": 4000
      }
    }
  }
}