{
  "id": "blue-flannel-shirt",
  "name": "Blue Flannel Shirt",
  "category": "Tops",
  "games": {
    "nl": {
      "orderable": true,
      "fashionThemes": [
        "Basic"
      ],
      "sellPrice": {
        "currency": "bells",
        "value": 105
      },
      "sources": [
        "Able Sisters"
      ],
      "buyPrices": [
        {
          "currency": "bells",
          "value": 420
        }
      ],
      "name": {
        "de": "Holzhackerhemd",
        "en-GB": "Blue Flannel Shirt",
        "en-US": "Blue Flannel Shirt",
        "es": "Camisa franela azul",
        "fr": "Pull flanelle bleu",
        "it": "Camicia grunge blu",
        "ja": "あおいネルシャツ"
      }
    }
  }
}