{
  "id": "brown-socks",
  "name": {
    "de": "Braunsocke",
    "en-GB": "Brown Socks",
    "en-US": "Brown Socks",
    "es": "Calcetín marrón",
    "fr": "Paire chauss. brunes",
    "it": "Paio calzini beige",
    "ja": "メランジソックス"
  },
  "category": "Socks",
  "games": {
    "nl": {
      "orderable": true,
      "fashionThemes": [
        "Basic"
      ],
      "sellPrice": {
        "currency": "bells",
        "value": 40
      },
      "sources": [
        "Kicks"
      ],
      "buyPrices": [
        {
          "currency": "bells",
          "value": 160
        }
      ]
    }
  }
}