{
  "id": "casual-chic-dress",
  "name": "Casual Chic Dress",
  "games": {
    "nh": {
      "sellPrice": {
        "currency": "bells",
        "value": 600
      },
      "buyPrices": [
        {
          "currency": "bells",
          "value": 2400
        }
      ],
      "variations": {
        "yellow": "Yellow",
        "light-blue": "Light blue",
        "pink": "Pink",
        "green": "Green",
        "navy-blue": "Navy blue",
        "purple": "Purple"
      },
      "name": {
        "en-US": "Casual Chic Dress",
        "en-GB": "Casual Chic Dress",
        "de": "Wickelkleid",
        "es": "Vestido de día chic",
        "fr": "Robe cache-cœur",
        "it": "Vestito casual-chic",
        "nl": "Omslagjurk",
        "zh-CN": "裹身裙",
        "zh-TW": "交叉V領綁帶連身裙",
        "jp": "カシュクールワンピース",
        "ko": "앞여밈 원피스"
      }
    }
  },
  "category": "Dresses"
}