{
  "id": "caterpillar-sofa",
  "name": {
    "de": "Raupensofa",
    "en-GB": "Caterpillar Sofa",
    "en-US": "Caterpillar Sofa",
    "es": "Sofá oruga",
    "fr": "Canapé bombyx",
    "it": "Sofà bruco",
    "ja": "いもむしソファ"
  },
  "category": "Furniture",
  "games": {
    "nl": {
      "orderable": false,
      "interiorThemes": [
        "Toy Shop"
      ],
      "set": "Insect",
      "sellPrice": {
        "currency": "bells",
        "value": 450
      },
      "sources": [
        "Bug Off"
      ]
    }
  }
}