{
  "id": "chic-windflower-wreath",
  "name": "Chic Windflower Wreath",
  "games": {
    "nh": {
      "sellPrice": {
        "currency": "bells",
        "value": 4800
      },
      "buyPrices": [
        {
          "currency": "bells",
          "value": 19200
        }
      ],
      "name": {
        "en-US": "Chic Windflower Wreath",
        "en-GB": "Chic Windflower Wreath",
        "de": "Edelanemonentürkranz",
        "es": "Corona anémona violeta",
        "fr": "Couronne anémones chic",
        "it": "Ghirlanda anemoni chic",
        "nl": "Chique anemonenkrans",
        "zh-CN": "典雅银莲花花环",
        "zh-TW": "典雅銀蓮花花圈",
        "jp": "シックなアネモネのリース",
        "ko": "시크 아네모네 리스"
      }
    }
  },
  "category": "Furniture"
}