{
  "id": "color-block-dress-shirt",
  "name": "Color-block Dress Shirt",
  "games": {
    "nh": {
      "orderable": true,
      "sources": [
        "Able Sisters"
      ],
      "sellPrice": {
        "currency": "bells",
        "value": 240
      },
      "buyPrices": [
        {
          "currency": "bells",
          "value": 960
        }
      ],
      "variations": {
        "blue": "Blue",
        "red": "Red",
        "green": "Green",
        "purple": "Purple",
        "yellow": "Yellow",
        "gray": "Gray"
      },
      "name": {
        "en-US": "Color-Block Dress Shirt",
        "en-GB": "Color-Block Dress Shirt",
        "de": "Zweifarbenhemd",
        "es": "Camisa bicolor",
        "fr": "Chemise bicolore",
        "it": "Camicia bicolore",
        "nl": "Tweekleurige overhemd",
        "zh-CN": "撞色有领衬衫",
        "zh-TW": "撞色有領襯衫",
        "jp": "ツートンのエリつきシャツ",
        "ko": "투톤 셔츠"
      }
    }
  },
  "category": "Tops"
}