{
  "id": "dandy-hat",
  "name": "Dandy Hat",
  "category": "Hats",
  "games": {
    "nl": {
      "orderable": true,
      "fashionThemes": [
        "Cute"
      ],
      "sellPrice": {
        "currency": "bells",
        "value": 80
      },
      "sources": [
        "Labelle"
      ],
      "buyPrices": [
        {
          "currency": "bells",
          "value": 320
        }
      ],
      "name": {
        "de": "Dandymütze",
        "en-GB": "Dandy Hat",
        "en-US": "Dandy Hat",
        "es": "Gorra bicolor",
        "fr": "Casquette de dandy",
        "it": "Basco colorato",
        "ja": "キャスケット"
      }
    },
    "nh": {
      "sellPrice": {
        "currency": "bells",
        "value": 275
      },
      "buyPrices": [
        {
          "currency": "bells",
          "value": 1100
        }
      ],
      "variations": {
        "camel": "Camel",
        "blue": "Blue",
        "green": "Green",
        "purple": "Purple",
        "gray": "Gray",
        "white": "White"
      },
      "name": {
        "en-US": "Dandy Hat",
        "en-GB": "Dandy Hat",
        "de": "Dandymütze",
        "es": "Gorra elegante",
        "fr": "Casquette de dandy",
        "it": "Berretto da dandy",
        "nl": "Krantenjongenspet",
        "zh-CN": "报童帽",
        "zh-TW": "報童帽",
        "jp": "キャスケット",
        "ko": "카스케트"
      }
    }
  }
}