{
  "id": "faux-fur-skirt",
  "name": "Faux-fur Skirt",
  "games": {
    "nh": {
      "sellPrice": {
        "currency": "bells",
        "value": 360
      },
      "buyPrices": [
        {
          "currency": "bells",
          "value": 1440
        }
      ],
      "variations": {
        "light-blue": "Light blue",
        "pink": "Pink",
        "red": "Red",
        "purple": "Purple",
        "yellow": "Yellow"
      },
      "name": {
        "en-US": "Faux-Fur Skirt",
        "en-GB": "Faux-Fur Skirt",
        "de": "Schleifchen-Kunstfellrock",
        "es": "Falda corta de pelo sintético",
        "fr": "Jupe en fausse fourrure",
        "it": "Gonna di ecopelliccia",
        "nl": "Imitatiebontrok",
        "zh-CN": "仿毛皮短裙",
        "zh-TW": "毛毛裙",
        "jp": "ファースカート",
        "ko": "인조털 치마"
      }
    }
  },
  "category": "Bottoms"
}