{
  "id": "fedora",
  "name": "Fedora",
  "games": {
    "nh": {
      "orderable": true,
      "sources": [
        "Able Sisters"
      ],
      "sellPrice": {
        "currency": "bells",
        "value": 275
      },
      "buyPrices": [
        {
          "currency": "bells",
          "value": 1100
        }
      ],
      "variations": {
        "beige": "Beige",
        "black": "Black",
        "green": "Green",
        "gray": "Gray",
        "white": "White",
        "red": "Red"
      },
      "name": {
        "en-US": "Fedora",
        "en-GB": "Fedora",
        "de": "Filzhut",
        "es": "Fedora",
        "fr": "Borsalino",
        "it": "Borsalino",
        "nl": "Gleufhoed",
        "zh-CN": "绅士帽",
        "zh-TW": "紳士帽",
        "jp": "なかおれハット",
        "ko": "페도라"
      }
    }
  },
  "category": "Hats"
}