{
  "id": "gar-model",
  "name": "Gar Model",
  "games": {
    "nh": {
      "sellPrice": {
        "currency": "bells",
        "value": 18000
      },
      "name": {
        "en-US": "Gar Model",
        "en-GB": "Gar Model",
        "de": "Knochenhechtmodell",
        "es": "Figura de pez caimán",
        "fr": "Modèle de gar",
        "it": "Replica di luccio",
        "nl": "Modelkaaimansnoek",
        "zh-CN": "雀鳝模型",
        "zh-TW": "雀鱔模型",
        "jp": "ガーのもけい",
        "ko": "가아 모형"
      }
    }
  },
  "category": "Furniture"
}