{
  "id": "honeybee",
  "name": "Honeybee",
  "category": "Bugs",
  "games": {
    "nl": {
      "orderable": false,
      "sellPrice": {
        "currency": "bells",
        "value": 100
      },
      "sources": [
        "Around flowers."
      ],
      "name": {
        "en-US": "Honeybee"
      }
    },
    "nh": {
      "orderable": false,
      "sources": [
        "North: Flying around flowers Mar-Jul (8am-5pm)",
        "South: Flying around flowers Sep-Jan (8am-5pm)"
      ],
      "sellPrice": {
        "currency": "bells",
        "value": 200
      },
      "name": {
        "en-US": "Honeybee",
        "en-GB": "Honeybee",
        "de": "Honigbiene",
        "es": "Abeja melífera",
        "fr": "Abeille naine",
        "it": "Ape operaia",
        "nl": "Honingbij",
        "zh-CN": "蜜蜂",
        "zh-TW": "蜜蜂",
        "jp": "ミツバチ",
        "ko": "꿀벌"
      }
    }
  }
}