{
  "id": "judogi",
  "name": "Judogi",
  "games": {
    "nh": {
      "sellPrice": {
        "currency": "bells",
        "value": 440
      },
      "buyPrices": [
        {
          "currency": "bells",
          "value": 1760
        }
      ],
      "variations": {
        "white": "White",
        "blue": "Blue"
      },
      "name": {
        "en-US": "Judogi",
        "en-GB": "Judogi",
        "de": "Judogi",
        "es": "Uniforme de judo",
        "fr": "Judogi",
        "it": "Tenuta da judo",
        "nl": "Judopak",
        "zh-CN": "柔道服",
        "zh-TW": "柔道服",
        "jp": "じゅうどうぎ",
        "ko": "유도복"
      }
    }
  },
  "category": "Dresses"
}