{
  "id": "kiwi-tank",
  "name": {
    "de": "Kiwitop",
    "en-GB": "Kiwi Tank",
    "en-US": "Kiwi Tank",
    "es": "Top kiwi",
    "fr": "Débardeur kiwi",
    "it": "Canotta kiwi",
    "ja": "キウイのふくN"
  },
  "category": "Tops",
  "games": {
    "nl": {
      "orderable": true,
      "interiorThemes": [
        "Rustic"
      ],
      "fashionThemes": [
        "Cute"
      ],
      "set": "Kiwi Outfit",
      "sellPrice": {
        "currency": "bells",
        "value": 70
      },
      "sources": [
        "Able Sisters (summer)"
      ],
      "buyPrices": [
        {
          "currency": "bells",
          "value": 280
        }
      ]
    }
  }
}