{
  "id": "kk-milonga",
  "name": "K.K. Milonga",
  "category": "Music",
  "games": {
    "nl": {
      "orderable": true,
      "interiorThemes": [
        "Antique",
        "Quirky"
      ],
      "sellPrice": {
        "currency": "bells",
        "value": 800
      },
      "sources": [
        "K.K. Slider",
        "T.I.Y."
      ],
      "buyPrices": [
        {
          "currency": "bells",
          "value": 3200
        }
      ],
      "name": {
        "en-US": "K.K. Milonga"
      }
    },
    "nh": {
      "orderable": true,
      "sellPrice": {
        "currency": "bells",
        "value": 800
      },
      "buyPrices": [
        {
          "currency": "bells",
          "value": 3200
        }
      ],
      "name": {
        "en-US": "K.K. Milonga",
        "en-GB": "K.K. Milonga",
        "de": "K.K. Milonga",
        "es": "Tota-Milonga",
        "fr": "Milonga Kéké",
        "it": "K.K. Milonga",
        "nl": "K.K.-Milonga",
        "zh-CN": "K.K.米隆加",
        "zh-TW": "K.K.米隆加",
        "jp": "けけのミロンガ",
        "ko": "K.K.밀롱가",
        "ru": "Милонга К. К."
      }
    }
  }
}