{
  "id": "knife-block",
  "name": "Knife Block",
  "games": {
    "nh": {
      "orderable": true,
      "sources": [
        "Nook's Cranny"
      ],
      "sellPrice": {
        "currency": "bells",
        "value": 300
      },
      "buyPrices": [
        {
          "currency": "bells",
          "value": 1200
        }
      ],
      "variations": {
        "natural": "Natural",
        "silver": "Silver",
        "black": "Black"
      },
      "name": {
        "en-US": "Knife Block",
        "en-GB": "Knife Block",
        "de": "Messerblock",
        "es": "Taco de cuchillos",
        "fr": "Bloc à couteaux",
        "it": "Ceppo portacoltelli",
        "nl": "Messenblok",
        "zh-CN": "菜刀架",
        "zh-TW": "菜刀架",
        "jp": "ほうちょうスタンド",
        "ko": "칼꽂이"
      }
    }
  },
  "category": "Furniture"
}