{
  "id": "nans-poster",
  "name": "Nan's Poster",
  "games": {
    "nh": {
      "sources": [
        "Nook Shopping after using Amiibo on Harvey's Island"
      ],
      "sellPrice": {
        "currency": "bells",
        "value": 250
      },
      "buyPrices": [
        {
          "currency": "bells",
          "value": 1000
        }
      ],
      "name": {
        "zh-CN": "墨墨的海报",
        "de": "Poster's von Zenobi",
        "en-GB": "Nan's Poster",
        "es": "Póster de Pécora",
        "fr": "Poster de Nana",
        "it": "Poster di Nan",
        "jp": "スミのポスター",
        "ko": "순이의 포스터",
        "nl": "Poster van Nan",
        "zh-TW": "墨墨的海報",
        "en-US": "Nan's Poster"
      }
    }
  },
  "category": "Photos"
}