{
  "id": "ocean-sunfish",
  "name": "Ocean Sunfish",
  "category": "Fish",
  "games": {
    "nl": {
      "orderable": false,
      "sellPrice": {
        "currency": "bells",
        "value": 4000
      },
      "sources": [
        "In the sea."
      ],
      "name": {
        "en-US": "Ocean Sunfish"
      }
    },
    "nh": {
      "orderable": false,
      "sources": [
        "North: Finned Shadows at Sea, Jul-Sep (4am-9pm)",
        "South: Finned Shadows at Sea, Jan-Mar (4am-9pm)"
      ],
      "sellPrice": {
        "currency": "bells",
        "value": 4000
      },
      "name": {
        "en-US": "Ocean Sunfish",
        "en-GB": "Ocean Sunfish",
        "de": "Mondfisch",
        "es": "Pez luna",
        "fr": "Lune de mer",
        "it": "Pesce luna",
        "nl": "Klompvis",
        "zh-CN": "翻车鱼",
        "zh-TW": "翻車魚",
        "jp": "マンボウ",
        "ko": "개복치"
      }
    }
  }
}