{
  "id": "pink-simple-cloth-wall",
  "name": "Pink Simple-cloth Wall",
  "games": {
    "nh": {
      "orderable": true,
      "sources": [
        "Nook's Cranny"
      ],
      "sellPrice": {
        "currency": "bells",
        "value": 187
      },
      "buyPrices": [
        {
          "currency": "bells",
          "value": 750
        }
      ],
      "name": {
        "en-US": "Pink Simple-Cloth Wall",
        "en-GB": "Pink Simple-Cloth Wall",
        "de": "Rosa-Textiltapete",
        "es": "Pared lisa salmón",
        "fr": "Mur textile saumon",
        "it": "Muro liscio rosa",
        "nl": "Roze gladde wand",
        "zh-CN": "粉红简约布面墙",
        "zh-TW": "粉紅簡約布面牆",
        "jp": "ピンクのシンプルクロス",
        "ko": "핑크 심플 벽지"
      }
    }
  },
  "category": "Wallpaper"
}