{
  "id": "pleather-skirt",
  "name": "Pleather Skirt",
  "games": {
    "nh": {
      "sellPrice": {
        "currency": "bells",
        "value": 325
      },
      "buyPrices": [
        {
          "currency": "bells",
          "value": 1300
        }
      ],
      "variations": {
        "black": "Black",
        "brown": "Brown",
        "beige": "Beige",
        "red": "Red",
        "blue": "Blue",
        "yellow": "Yellow"
      },
      "name": {
        "en-US": "Pleather Skirt",
        "en-GB": "Pleather Skirt",
        "de": "Kunstlederrock",
        "es": "Falda corta de polipiel",
        "fr": "Jupe en similicuir",
        "it": "Gonna in ecopelle",
        "nl": "Kunstleren rokje",
        "zh-CN": "皮裙",
        "zh-TW": "皮裙",
        "jp": "レザースカート",
        "ko": "가죽 치마"
      }
    }
  },
  "category": "Bottoms"
}