{
  "id": "quilted-jacket",
  "name": "Quilted Jacket",
  "games": {
    "nh": {
      "sellPrice": {
        "currency": "bells",
        "value": 350
      },
      "buyPrices": [
        {
          "currency": "bells",
          "value": 1400
        }
      ],
      "variations": {
        "pink": "Pink",
        "brown": "Brown",
        "lime": "Lime",
        "blue": "Blue",
        "green": "Green"
      },
      "name": {
        "en-US": "Quilted Jacket",
        "en-GB": "Quilted Jacket",
        "de": "Steppjacke",
        "es": "Chaquetón acolchado",
        "fr": "Veste matelassée",
        "it": "Giacca trapuntata",
        "nl": "Open gewatteerde jas",
        "zh-CN": "菱格缝线外套",
        "zh-TW": "菱格縫線外套",
        "jp": "キルティングジャケット",
        "ko": "퀼트 재킷"
      }
    }
  },
  "category": "Tops"
}