{
  "id": "red-hood",
  "name": {
    "de": "Rothaube",
    "en-GB": "Red Hood",
    "en-US": "Red Hood",
    "es": "Caperuza roja",
    "fr": "Chaperon rouge",
    "it": "Cappuccio rosso",
    "ja": "あかずきん"
  },
  "category": "Hats",
  "games": {
    "nl": {
      "orderable": true,
      "interiorThemes": [
        "Fairy Tale"
      ],
      "fashionThemes": [
        "Cute"
      ],
      "sellPrice": {
        "currency": "bells",
        "value": 100
      },
      "sources": [
        "Labelle"
      ],
      "buyPrices": [
        {
          "currency": "bells",
          "value": 400
        }
      ]
    }
  }
}