{
  "id": "retro-sweater",
  "name": "Retro Sweater",
  "games": {
    "nh": {
      "sellPrice": {
        "currency": "bells",
        "value": 300
      },
      "buyPrices": [
        {
          "currency": "bells",
          "value": 1200
        }
      ],
      "variations": {
        "purple": "Purple",
        "yellow": "Yellow",
        "white": "White",
        "blue": "Blue"
      },
      "name": {
        "en-US": "Retro Sweater",
        "en-GB": "Retro Sweater",
        "de": "Design-Pulli",
        "es": "Jersey pop",
        "fr": "Pull art déco",
        "it": "Maglione variopinto",
        "nl": "Trui met print",
        "zh-CN": "品位高雅毛衣",
        "zh-TW": "品味高尚毛衣",
        "jp": "ハイセンスなセーター",
        "ko": "하이센스 스웨터"
      }
    }
  },
  "category": "Tops"
}