{
  "id": "rice-grasshopper",
  "name": "Rice Grasshopper",
  "category": "Bugs",
  "games": {
    "nl": {
      "orderable": false,
      "sellPrice": {
        "currency": "bells",
        "value": 400
      },
      "sources": [
        "In grassy patches."
      ],
      "name": {
        "en-US": "Rice Grasshopper"
      }
    },
    "nh": {
      "orderable": false,
      "sources": [
        "North: On the ground, Aug-Nov (8am-7pm)",
        "South: On the ground, Feb-May (8am-7pm)"
      ],
      "sellPrice": {
        "currency": "bells",
        "value": 400
      },
      "name": {
        "en-US": "Rice Grasshopper",
        "en-GB": "Rice Grasshopper",
        "de": "Heuschrecke",
        "es": "Langosta",
        "fr": "Criquet",
        "it": "Locusta",
        "nl": "Rijstsprinkhaan",
        "zh-CN": "稻蝗",
        "zh-TW": "稻蝗",
        "jp": "イナゴ",
        "ko": "메뚜기"
      }
    }
  }
}