{
  "id": "rodeos-photo",
  "name": "Rodeo's Photo",
  "games": {
    "nh": {
      "sellPrice": {
        "currency": "bells",
        "value": 10
      },
      "name": {
        "zh-CN": "罗迪欧的照片",
        "de": "Foto's von Toro",
        "en-GB": "Rodeo's Photo",
        "es": "Foto de Rodeo",
        "fr": "Photo de Flèche",
        "it": "Foto di Rodeo",
        "jp": "ロデオのしゃしん",
        "ko": "로데오의 사진",
        "nl": "Foto van Rodeo",
        "zh-TW": "羅迪歐的照片",
        "en-US": "Rodeo's Photo"
      }
    }
  },
  "category": "Photos"
}