{
  "id": "rugby-tee",
  "name": "Rugby Tee",
  "category": "Tops",
  "games": {
    "nl": {
      "orderable": true,
      "fashionThemes": [
        "Rock-n'-roll"
      ],
      "sellPrice": {
        "currency": "bells",
        "value": 90
      },
      "sources": [
        "Able Sisters"
      ],
      "buyPrices": [
        {
          "currency": "bells",
          "value": 360
        }
      ],
      "name": {
        "de": "Rugby-Shirt",
        "en-GB": "Rugby Tee",
        "en-US": "Rugby Tee",
        "es": "Camiseta rugby",
        "fr": "T-shirt rugby",
        "it": "Maglietta rugby",
        "ja": "めだつボーダーのふく"
      }
    }
  }
}