{
  "id": "school-cap",
  "name": "School Cap",
  "category": "Hats",
  "games": {
    "nl": {
      "orderable": true,
      "fashionThemes": [
        "Sporty"
      ],
      "sellPrice": {
        "currency": "bells",
        "value": 90
      },
      "sources": [
        "DLC (KOR)"
      ],
      "buyPrices": [
        {
          "currency": "bells",
          "value": 360
        }
      ],
      "name": {
        "de": "Schulmütze (blau)",
        "en-GB": "School Cap",
        "en-US": "School Cap",
        "es": "Gorra colegio azul",
        "fr": "Casqu. écol. bleue",
        "it": "Cappellino azzurro",
        "ja": "あおしろのぼうし"
      }
    }
  }
}