{
  "id": "sleeveless-dress-shirt",
  "name": "Sleeveless Dress Shirt",
  "games": {
    "nh": {
      "sellPrice": {
        "currency": "bells",
        "value": 240
      },
      "buyPrices": [
        {
          "currency": "bells",
          "value": 960
        }
      ],
      "variations": {
        "white": "White",
        "pink": "Pink",
        "green": "Green",
        "orange": "Orange",
        "blue": "Blue"
      },
      "name": {
        "en-US": "Sleeveless Dress Shirt",
        "en-GB": "Sleeveless Dress Shirt",
        "de": "Sommeranzughemd",
        "es": "Camisa sin mangas",
        "fr": "Chemise sans manches",
        "it": "Camicia smanicata",
        "nl": "",
        "zh-CN": "无袖有领衬衫",
        "zh-TW": "無袖有領襯衫",
        "jp": "ノースリーブえりつきシャツ",
        "ko": "민소매 셔츠"
      }
    }
  },
  "category": "Tops"
}