{
  "id": "strawberry-tank",
  "name": {
    "de": "Erdbeertop",
    "en-GB": "Strawberry Tank",
    "en-US": "Strawberry Tank",
    "es": "Top fresa",
    "fr": "Débardeur fraise",
    "it": "Canotta fragola",
    "ja": "いちごのふくN"
  },
  "category": "Tops",
  "games": {
    "nl": {
      "orderable": true,
      "fashionThemes": [
        "Cute"
      ],
      "set": "Strawberry Outfit",
      "sellPrice": {
        "currency": "bells",
        "value": 70
      },
      "sources": [
        "Able Sisters (summer)"
      ],
      "buyPrices": [
        {
          "currency": "bells",
          "value": 280
        }
      ]
    }
  }
}