{
  "id": "streetlamp",
  "name": "Streetlamp",
  "games": {
    "nh": {
      "orderable": true,
      "sources": [
        "Nook Miles System"
      ],
      "sellPrice": {
        "currency": "bells",
        "value": 5000
      },
      "buyPrices": [
        {
          "currency": "miles",
          "value": 1000
        }
      ],
      "variations": {
        "green": "Green",
        "brown": "Brown",
        "white": "White",
        "black": "Black"
      },
      "name": {
        "en-US": "Streetlamp",
        "en-GB": "Streetlamp",
        "de": "Straßenlampe",
        "es": "Farola",
        "fr": "Réverbère",
        "it": "Lampione",
        "nl": "Straatlantaarn",
        "zh-CN": "路灯",
        "zh-TW": "路燈",
        "jp": "がいとう",
        "ko": "가로등"
      }
    }
  },
  "category": "Furniture"
}