{
  "id": "striped-maxi-dress",
  "name": "Striped Maxi Dress",
  "games": {
    "nh": {
      "sellPrice": {
        "currency": "bells",
        "value": 350
      },
      "buyPrices": [
        {
          "currency": "bells",
          "value": 1400
        }
      ],
      "variations": {
        "red": "Red",
        "blue": "Blue",
        "green": "Green",
        "orange": "Orange"
      },
      "name": {
        "en-US": "Striped Maxi Dress",
        "en-GB": "Striped Maxi Dress",
        "de": "Streifenmaxikleid",
        "es": "Vestido largo a rayas",
        "fr": "Maxi robe à rayures",
        "it": "Vestito lungo a righe",
        "nl": "Gestreepte maxi-jurk",
        "zh-CN": "条纹长连身裙",
        "zh-TW": "條紋連身長裙",
        "jp": "ストライプのマキシワンピ",
        "ko": "줄무늬 맥시 원피스"
      }
    }
  },
  "category": "Dresses"
}