{
  "id": "tailors-ticket",
  "name": "Tailors Ticket",
  "games": {
    "nh": {
      "sellPrice": {
        "currency": "bells",
        "value": 250
      },
      "name": {
        "zh-CN": "裁缝屋优惠券",
        "de": "Schneiderei-Coupon's",
        "en-GB": "Tailors Ticket",
        "es": "Cupón de la sastrería",
        "fr": "Ticket atelier de couture",
        "it": "Coupon della sartoria",
        "jp": "したてやクーポン",
        "ko": "옷가게 쿠폰",
        "nl": "Kleermakersbon",
        "zh-TW": "裁縫屋優惠券",
        "en-US": "Tailors Ticket"
      }
    }
  },
  "category": "Usables"
}