{
  "id": "tea-tansu",
  "name": "Tea Tansu",
  "category": "Furniture",
  "games": {
    "nl": {
      "orderable": true,
      "interiorThemes": [
        "Harmonious",
        "Rustic"
      ],
      "set": "Zen",
      "sellPrice": {
        "currency": "bells",
        "value": 400
      },
      "sources": [
        "Nookling stores"
      ],
      "buyPrices": [
        {
          "currency": "bells",
          "value": 1600
        }
      ],
      "name": {
        "de": "Tansu-Teeschrank",
        "en-GB": "Tea Tansu",
        "en-US": "Tea Tansu",
        "es": "Tansu de té",
        "fr": "Meuble à thé",
        "it": "Tansu da tè",
        "ja": "ちゃだんす"
      }
    }
  }
}