{
  "id": "team-ntdo-tee",
  "name": {
    "de": "Rotsaumshirt",
    "en-GB": "Team NTDO Tee",
    "en-US": "Team NTDO Tee",
    "es": "Camiseta NTDO",
    "fr": "T-shirt équipe NTDO",
    "it": "Maglietta grigia",
    "ja": "はしがあかいふく"
  },
  "category": "Tops",
  "games": {
    "nl": {
      "orderable": true,
      "fashionThemes": [
        "Sporty"
      ],
      "sellPrice": {
        "currency": "bells",
        "value": 80
      },
      "sources": [
        "Able Sisters"
      ],
      "buyPrices": [
        {
          "currency": "bells",
          "value": 320
        }
      ]
    }
  }
}