{
  "id": "toy-centipede",
  "name": "Toy Centipede",
  "games": {
    "nh": {
      "sellPrice": {
        "currency": "bells",
        "value": 50
      },
      "buyPrices": [
        {
          "currency": "bells",
          "value": 200
        }
      ],
      "name": {
        "en-US": "Toy Centipede",
        "en-GB": "Toy Centipede",
        "de": "Spielzeug-Hundertfüßer",
        "es": "Ciempiés de pega",
        "fr": "Mille-Pattes en plastique",
        "it": "Centopiedi finto",
        "nl": "Fopduizendpoot",
        "zh-CN": "玩具蜈蚣",
        "zh-TW": "玩具蜈蚣",
        "jp": "おもちゃのムカデ",
        "ko": "장난감 지네"
      }
    }
  },
  "category": "Furniture"
}