{
  "id": "track-jacket",
  "name": "Track Jacket",
  "games": {
    "nh": {
      "sellPrice": {
        "currency": "bells",
        "value": 227
      },
      "buyPrices": [
        {
          "currency": "bells",
          "value": 910
        }
      ],
      "variations": {
        "navy-blue": "Navy blue",
        "gray": "Gray",
        "white": "White",
        "red": "Red",
        "light-blue": "Light blue",
        "green": "Green",
        "blue": "Blue"
      },
      "name": {
        "en-US": "Track Jacket",
        "en-GB": "Track Jacket",
        "de": "Aufwärmjacke",
        "es": "Sudadera urbana",
        "fr": "Veste survêt de sport",
        "it": "Maglia da ginnastica",
        "nl": "Atletiekjack",
        "zh-CN": "健身运动服",
        "zh-TW": "健身運動服",
        "jp": "スポーツジャージ",
        "ko": "스포츠 트레이닝복"
      }
    }
  },
  "category": "Tops"
}