{
  "id": "tuckers-photo",
  "name": "Tucker's Photo",
  "games": {
    "nh": {
      "sellPrice": {
        "currency": "bells",
        "value": 10
      },
      "name": {
        "zh-CN": "阿原的照片",
        "de": "Foto's von Thorsten",
        "en-GB": "Tucker's Photo",
        "es": "Foto de Pirolo",
        "fr": "Photo de Barry",
        "it": "Foto di Sventolo",
        "jp": "はじめのしゃしん",
        "ko": "맘모의 사진",
        "nl": "Foto van Tucker",
        "zh-TW": "阿原的照片",
        "en-US": "Tucker's Photo"
      }
    }
  },
  "category": "Photos"
}