{
  "id": "wooden-storage-shed",
  "name": "Wooden Storage Shed",
  "games": {
    "nh": {
      "version": "2.0",
      "recipe": {
        "wood": 30,
        "hardwood": 30,
        "softwood": 30,
        "iron-nugget": 10
      },
      "variations": {
        "brown": "Brown",
        "ivory": "Ivory",
        "green": "Green",
        "blue": "Blue",
        "red": "Red",
        "dark-brown": "Dark brown",
        "ash": "Ash",
        "black": "Black"
      }
    }
  },
  "category": "Furniture"
}