{
  "gender": "female",
  "species": "squirrel",
  "birthday": "7-15",
  "games": {
    "ww": {
      "personality": "normal",
      "clothes": "gelato-tee",
      "song": "DJ K.K.",
      "phrase": "hulaaaa",
      "quote": "Relax!"
    },
    "cf": {
      "personality": "normal",
      "clothes": "gelato-tee",
      "song": "DJ K.K.",
      "phrase": "hulaaaa"
    },
    "nl": {
      "personality": "normal",
      "clothes": "gelato-tee",
      "song": "DJ K.K.",
      "phrase": "hulaaaa",
      "skill": "Shadow puppetry",
      "goal": "Volleyball player",
      "fear": "Skeleton Hood",
      "quote": "New brooms sweep clean.",
      "siblings": "Second of 4 kids",
      "dislikedStyle": "Iconic",
      "coffee": {
        "beans": "Kilamanjaro",
        "milk": "A little bit of milk",
        "sugar": "One spoonful of sugar"
      },
      "favoriteColors": [
        "colorful"
      ],
      "favoriteStyles": [
        "Cute/Fancy"
      ]
    },
    "nh": {
      "personality": "normal",
      "phrase": "hulaaaa",
      "song": "Pondering",
      "hobby": "Music",
      "subtype": "B",
      "quote": "New brooms sweep clean.",
      "clothes": "striped-maxi-dress"
    }
  },
  "name": "Caroline",
  "id": "caroline"
}